jupyterlab_markdown_switch_tab_scrolling_fix/__init__.py
jupyterlab_markdown_switch_tab_scrolling_fix/_version.py
jupyterlab_markdown_switch_tab_scrolling_fix-1.0.5.data/data/share/jupyter/labextensions/jupyterlab_markdown_switch_tab_scrolling_fix/package.json
jupyterlab_markdown_switch_tab_scrolling_fix-1.0.5.data/data/share/jupyter/labextensions/jupyterlab_markdown_switch_tab_scrolling_fix/static/509.80df41fedc843e7a39cd.js
jupyterlab_markdown_switch_tab_scrolling_fix-1.0.5.data/data/share/jupyter/labextensions/jupyterlab_markdown_switch_tab_scrolling_fix/static/728.59d1937fbd464ba1aea8.js
jupyterlab_markdown_switch_tab_scrolling_fix-1.0.5.data/data/share/jupyter/labextensions/jupyterlab_markdown_switch_tab_scrolling_fix/static/remoteEntry.2159371e2634b2a1506b.js
jupyterlab_markdown_switch_tab_scrolling_fix-1.0.5.data/data/share/jupyter/labextensions/jupyterlab_markdown_switch_tab_scrolling_fix/static/style.js
jupyterlab_markdown_switch_tab_scrolling_fix-1.0.5.data/data/share/jupyter/labextensions/jupyterlab_markdown_switch_tab_scrolling_fix/static/third-party-licenses.json
jupyterlab_markdown_switch_tab_scrolling_fix-1.0.5.data/data/share/jupyter/labextensions/jupyterlab_markdown_switch_tab_scrolling_fix/install.json
jupyterlab_markdown_switch_tab_scrolling_fix-1.0.5.dist-info/METADATA
jupyterlab_markdown_switch_tab_scrolling_fix-1.0.5.dist-info/WHEEL
jupyterlab_markdown_switch_tab_scrolling_fix-1.0.5.dist-info/licenses/LICENSE
jupyterlab_markdown_switch_tab_scrolling_fix-1.0.5.dist-info/RECORD
