Metadata-Version: 2.4
Name: jupyterlab_markdown_switch_tab_scrolling_fix
Version: 1.0.5
Summary: Jupyterlab bugfix (disguised as extension) to help with the problem of Markdown files getting scrolled uncontrollably when images are gettng loaded into the view when switching tab back and forth
Project-URL: Homepage, https://github.com/stellarshenson/jupyterlab_markdown_switch_tab_scrolling_fix
Project-URL: Bug Tracker, https://github.com/stellarshenson/jupyterlab_markdown_switch_tab_scrolling_fix/issues
Project-URL: Repository, https://github.com/stellarshenson/jupyterlab_markdown_switch_tab_scrolling_fix.git
Author-email: Stellars Henson <konrad.jelen@gmail.com>
License: BSD 3-Clause License
License-File: LICENSE
Keywords: jupyter,jupyterlab,jupyterlab-extension
Classifier: Framework :: Jupyter
Classifier: Framework :: Jupyter :: JupyterLab
Classifier: Framework :: Jupyter :: JupyterLab :: 4
Classifier: Framework :: Jupyter :: JupyterLab :: Extensions
Classifier: Framework :: Jupyter :: JupyterLab :: Extensions :: Prebuilt
Classifier: License :: OSI Approved :: BSD License
Classifier: Programming Language :: Python
Classifier: Programming Language :: Python :: 3
Classifier: Programming Language :: Python :: 3.9
Classifier: Programming Language :: Python :: 3.10
Classifier: Programming Language :: Python :: 3.11
Classifier: Programming Language :: Python :: 3.12
Classifier: Programming Language :: Python :: 3.13
Requires-Python: >=3.9
